zenconf
