Metadata-Version: 1.0
Name: zenconf
Version: 0.1.4
Summary: Simple configuration system based on recursively merging dicts.
Home-page: https://github.com/nws-cip/zenconf
Author: Alan Bates
Author-email: alan.bates@news.co.uk
License: MIT
Platform: UNKNOWN
